kubesmartservice/__init__.py
kubesmartservice/core.py
kubesmartservice/py.typed
kubesmartservice-0.1.1.dist-info/licenses/LICENSE
kubesmartservice-0.1.1.dist-info/METADATA
kubesmartservice-0.1.1.dist-info/WHEEL
kubesmartservice-0.1.1.dist-info/top_level.txt
kubesmartservice-0.1.1.dist-info/RECORD
