Metadata-Version: 2.4
Name: kubeSmartService
Version: 0.1.1
Summary: Smart Kubernetes service resolver for Python web apps with health-check and failover
Author-email: Yassir AIT EL AIZZI <yassiraitelaizzi@gmail.com>
License: MIT
Project-URL: Homepage, https://github.com/example/kubeSmartService
Project-URL: Repository, https://github.com/example/kubeSmartService
Project-URL: Issues, https://github.com/example/kubeSmartService/issues
Keywords: kubernetes,service,failover,healthcheck,django,flask
Classifier: Development Status :: 3 - Alpha
Classifier: Intended Audience :: Developers
Classifier: License :: OSI Approved :: MIT License
Classifier: Programming Language :: Python
Classifier: Programming Language :: Python :: 3
Classifier: Programming Language :: Python :: 3.8
Classifier: Programming Language :: Python :: 3.9
Classifier: Programming Language :: Python :: 3.10
Classifier: Programming Language :: Python :: 3.11
Classifier: Programming Language :: Python :: 3.12
Classifier: Topic :: Internet :: WWW/HTTP
Classifier: Topic :: System :: Distributed Computing
Requires-Python: >=3.8
License-File: LICENSE
Requires-Dist: kubernetes>=29.0.0
Dynamic: license-file
